model_comparator/__init__.py
model_comparator/comparator.py
tests/__init__.py
tests/test_comparator.py
model_comparator-1.0.2.dist-info/LICENSE
model_comparator-1.0.2.dist-info/METADATA
model_comparator-1.0.2.dist-info/WHEEL
model_comparator-1.0.2.dist-info/top_level.txt
model_comparator-1.0.2.dist-info/RECORD
